ralph/__init__.py
ralph/__main__.py
ralph/cli.py
ralph/conf.py
ralph/exceptions.py
ralph/filters.py
ralph/logger.py
ralph/parsers.py
ralph/utils.py
ralph/api/__init__.py
ralph/api/forwarding.py
ralph/api/models.py
ralph/api/auth/__init__.py
ralph/api/auth/basic.py
ralph/api/auth/oidc.py
ralph/api/auth/user.py
ralph/api/routers/__init__.py
ralph/api/routers/health.py
ralph/api/routers/statements.py
ralph/backends/__init__.py
ralph/backends/loader.py
ralph/backends/data/__init__.py
ralph/backends/data/async_es.py
ralph/backends/data/async_lrs.py
ralph/backends/data/async_mongo.py
ralph/backends/data/async_ws.py
ralph/backends/data/base.py
ralph/backends/data/clickhouse.py
ralph/backends/data/es.py
ralph/backends/data/fs.py
ralph/backends/data/ldp.py
ralph/backends/data/lrs.py
ralph/backends/data/mixins.py
ralph/backends/data/mongo.py
ralph/backends/data/s3.py
ralph/backends/data/swift.py
ralph/backends/lrs/__init__.py
ralph/backends/lrs/async_es.py
ralph/backends/lrs/async_mongo.py
ralph/backends/lrs/base.py
ralph/backends/lrs/clickhouse.py
ralph/backends/lrs/es.py
ralph/backends/lrs/fs.py
ralph/backends/lrs/mongo.py
ralph/models/__init__.py
ralph/models/converter.py
ralph/models/selector.py
ralph/models/validator.py
ralph/models/edx/__init__.py
ralph/models/edx/base.py
ralph/models/edx/browser.py
ralph/models/edx/server.py
ralph/models/edx/bookmark/__init__.py
ralph/models/edx/bookmark/statements.py
ralph/models/edx/bookmark/fields/__init__.py
ralph/models/edx/bookmark/fields/events.py
ralph/models/edx/certificate/__init__.py
ralph/models/edx/certificate/statements.py
ralph/models/edx/certificate/fields/__init__.py
ralph/models/edx/certificate/fields/events.py
ralph/models/edx/cohort/__init__.py
ralph/models/edx/cohort/statements.py
ralph/models/edx/cohort/fields/__init__.py
ralph/models/edx/cohort/fields/events.py
ralph/models/edx/content_library_interaction/__init__.py
ralph/models/edx/content_library_interaction/statements.py
ralph_malph-5.0.1.dist-info/LICENSE.md
ralph_malph-5.0.1.dist-info/METADATA
ralph_malph-5.0.1.dist-info/WHEEL
ralph_malph-5.0.1.dist-info/entry_points.txt
ralph_malph-5.0.1.dist-info/top_level.txt
ralph_malph-5.0.1.dist-info/zip-safe
ralph_malph-5.0.1.dist-info/RECORD
