Metadata-Version: 2.1
Name: ralph-malph
Version: 5.0.1
Summary: Ralph, the ultimate Learning Record Store (and more!) for your learning analytics.
Author-email: "Open FUN (France Université Numérique)" <fun.dev@fun-mooc.fr>
License: MIT License
Project-URL: Homepage, https://openfun.github.io/ralph/
Project-URL: Bug Tracker, https://github.com/openfun/ralph/issues
Project-URL: Changelog, https://github.com/openfun/ralph/blob/main/CHANGELOG.md
Project-URL: Repository, https://github.com/openfun/ralph
Keywords: LRS,Analytics,xAPI,Open edX
Classifier: Development Status :: 5 - Production/Stable
Classifier: Intended Audience :: Developers
Classifier: License :: OSI Approved :: MIT License
Classifier: Natural Language :: English
Classifier: Programming Language :: Python :: 3
Classifier: Programming Language :: Python :: 3.8
Classifier: Programming Language :: Python :: 3.9
Classifier: Programming Language :: Python :: 3.10
Classifier: Programming Language :: Python :: 3.11
Classifier: Programming Language :: Python :: 3.12
Requires-Python: >=3.8
License-File: LICENSE.md
Requires-Dist: importlib-metadata <8.0,>=7.0.1
Requires-Dist: langcodes >=3.2.0
Requires-Dist: pydantic[email] <3.0,>=2.5.3
Requires-Dist: pydantic-settings <3.0,>=2.1.0
Requires-Dist: rfc3987 >=1.3.0
Provides-Extra: backend-clickhouse
Requires-Dist: clickhouse-connect[numpy,pandas] <0.6 ; extra == 'backend-clickhouse'
Requires-Dist: python-dateutil >=2.8.2 ; extra == 'backend-clickhouse'
Provides-Extra: backend-es
Requires-Dist: elasticsearch[async] >=8.0.0 ; extra == 'backend-es'
Provides-Extra: backend-ldp
Requires-Dist: ovh >=1.0.0 ; extra == 'backend-ldp'
Requires-Dist: requests >=2.0.0 ; extra == 'backend-ldp'
Provides-Extra: backend-lrs
Requires-Dist: httpx <0.25.0 ; extra == 'backend-lrs'
Provides-Extra: backend-mongo
Requires-Dist: motor[srv] >=3.3.0 ; extra == 'backend-mongo'
Requires-Dist: pymongo[srv] >=4.0.0 ; extra == 'backend-mongo'
Requires-Dist: python-dateutil >=2.8.2 ; extra == 'backend-mongo'
Provides-Extra: backend-s3
Requires-Dist: boto3 >=1.24.70 ; extra == 'backend-s3'
Requires-Dist: botocore >=1.27.71 ; extra == 'backend-s3'
Requires-Dist: requests-toolbelt >=1.0.0 ; extra == 'backend-s3'
Provides-Extra: backend-swift
Requires-Dist: python-keystoneclient >=5.0.0 ; extra == 'backend-swift'
Requires-Dist: python-swiftclient >=4.0.0 ; extra == 'backend-swift'
Provides-Extra: backend-ws
Requires-Dist: websockets >=10.3 ; extra == 'backend-ws'
Provides-Extra: backends
Requires-Dist: ralph-malph[backend-clickhouse,backend-es,backend-ldp,backend-lrs,backend-mongo,backend-s3,backend-swift] ; extra == 'backends'
Provides-Extra: ci
Requires-Dist: twine ==5.1.0 ; extra == 'ci'
Provides-Extra: cli
Requires-Dist: bcrypt >=4.0.0 ; extra == 'cli'
Requires-Dist: click >=8.1.0 ; extra == 'cli'
Requires-Dist: click-option-group >=0.5.0 ; extra == 'cli'
Requires-Dist: sentry-sdk[fastapi] >=1.9.0 ; extra == 'cli'
Provides-Extra: dev
Requires-Dist: anyio <4.4.1 ; extra == 'dev'
Requires-Dist: black ==24.4.2 ; extra == 'dev'
Requires-Dist: cryptography ==42.0.7 ; extra == 'dev'
Requires-Dist: factory-boy ==3.3.0 ; extra == 'dev'
Requires-Dist: logging-gelf ==0.0.32 ; extra == 'dev'
Requires-Dist: mike ==2.1.1 ; extra == 'dev'
Requires-Dist: mkdocs ==1.6.0 ; extra == 'dev'
Requires-Dist: mkdocs-click ==0.8.1 ; extra == 'dev'
Requires-Dist: mkdocs-material ==9.5.25 ; extra == 'dev'
Requires-Dist: mkdocstrings[python-legacy] ==0.25.1 ; extra == 'dev'
Requires-Dist: moto ==5.0.9 ; extra == 'dev'
Requires-Dist: mypy ==1.10.0 ; extra == 'dev'
Requires-Dist: neoteroi-mkdocs ==1.0.5 ; extra == 'dev'
Requires-Dist: polyfactory ==2.16.0 ; extra == 'dev'
Requires-Dist: pyfakefs ==5.5.0 ; extra == 'dev'
Requires-Dist: pymdown-extensions ==10.8.1 ; extra == 'dev'
Requires-Dist: pytest <8.0.0 ; extra == 'dev'
Requires-Dist: pytest-cov ==5.0.0 ; extra == 'dev'
Requires-Dist: pytest-httpx <0.23.0 ; extra == 'dev'
Requires-Dist: requests-mock ==1.12.1 ; extra == 'dev'
Requires-Dist: responses ==0.24.1 ; extra == 'dev'
Requires-Dist: ruff ==0.4.7 ; extra == 'dev'
Requires-Dist: types-python-dateutil ==2.9.0.20240316 ; extra == 'dev'
Requires-Dist: types-python-jose ==3.3.4.20240106 ; extra == 'dev'
Requires-Dist: types-requests <2.32.0.20240603 ; extra == 'dev'
Requires-Dist: types-cachetools ==5.3.0.7 ; extra == 'dev'
Provides-Extra: full
Requires-Dist: ralph-malph[backends,cli,lrs] ; extra == 'full'
Provides-Extra: lrs
Requires-Dist: bcrypt ==4.1.3 ; extra == 'lrs'
Requires-Dist: fastapi ==0.111.0 ; extra == 'lrs'
Requires-Dist: cachetools ==5.3.3 ; extra == 'lrs'
Requires-Dist: httpx <0.25.0 ; extra == 'lrs'
Requires-Dist: sentry-sdk ==2.4.0 ; extra == 'lrs'
Requires-Dist: python-jose ==3.3.0 ; extra == 'lrs'
Requires-Dist: uvicorn[standard] ==0.30.1 ; extra == 'lrs'
